btcturk/__init__.py
btcturk/btcturk.py
btcturk-0.0.5.dist-info/METADATA
btcturk-0.0.5.dist-info/RECORD
btcturk-0.0.5.dist-info/WHEEL
btcturk-0.0.5.dist-info/top_level.txt
