Metadata-Version: 2.1
Name: btcturk
Version: 0.0.5
Summary: Python btcturk.com API wrapper.
Home-page: https://github.com/erhan/pybtcturk
Author: Erhan BUTE
Author-email: erhan@pysoft.io
License: MIT
Keywords: btcturk,bitcoin,exchange,btc,eth,xrp
Platform: UNKNOWN
Classifier: Intended Audience :: Developers
Classifier: License :: OSI Approved :: MIT License
Classifier: Operating System :: OS Independent
Classifier: Programming Language :: Python :: 2
Classifier: Programming Language :: Python :: 2.7
Classifier: Programming Language :: Python :: 3
Classifier: Programming Language :: Python :: 3.3
Classifier: Programming Language :: Python :: 3.4
Classifier: Programming Language :: Python :: 3.5
Classifier: Programming Language :: Python :: 3.6
Classifier: Programming Language :: Python
Classifier: Topic :: Office/Business :: Financial
Requires-Dist: requests
